structdbrest/__init__.py
structdbrest/data_classes.py
structdbrest/query.py
structdbrest-0.0.1.dist-info/LICENSE
structdbrest-0.0.1.dist-info/METADATA
structdbrest-0.0.1.dist-info/WHEEL
structdbrest-0.0.1.dist-info/top_level.txt
structdbrest-0.0.1.dist-info/zip-safe
structdbrest-0.0.1.dist-info/RECORD
